{
  "rows":[{
      "id":0,
      "picTitle":"节日图片",
      "picSrc":"./images2/1.jpg"
  },{
    "id":1,
    "picTitle":"紫色图片",
    "picSrc":"./images2/2.jpg"
},{
  "id":2,
  "picTitle":"水墨画卷图片",
  "picSrc":"./images2/3.jpg"
},{
  "id":3,
  "picTitle":"卡通厨师图片",
  "picSrc":"./images2/4.jpg"
},{
  "id":4,
  "picTitle":"日式庭院图片",
  "picSrc":"./images2/5.jpg"
},{
  "id":5,
  "picTitle":"荷花图片",
  "picSrc":"./images2/6.jpg"
},{
  "id":6,
  "picTitle":"绿草图片",
  "picSrc":"./images2/7.jpg"
},{
  "id":7,
  "picTitle":"精致楼房图片",
  "picSrc":"./images2/8.jpg"
},{
  "id":8,
  "picTitle":"春天图片",
  "picSrc":"./images2/3.jpg"
},{
  "id":9,
  "picTitle":"向日葵图片",
  "picSrc":"./images2/10.jpg"
},{
  "id":10,
  "picTitle":"幼儿园图片",
  "picSrc":"./images2/11.jpg"
},{
  "id":11,
  "picTitle":"春节灯笼图片",
  "picSrc":"./images2/12.jpg"
},{
  "id":12,
  "picTitle":"大厦图片",
  "picSrc":"./images2/13.jpg"
},{
  "id":13,
  "picTitle":"梨花图片",
  "picSrc":"./images2/14.jpg"
},{
  "id":14,
  "picTitle":"咖啡图片",
  "picSrc":"./images2/15.jpg"
},{
  "id":15,
  "picTitle":"老爷车图片",
  "picSrc":"./images2/16.jpg"
},{
  "id":16,
  "picTitle":"民族图片",
  "picSrc":"./images2/17.jpg"
},{
  "id":17,
  "picTitle":"春节灯笼图片",
  "picSrc":"./images2/18.jpg"
},{
  "id":18,
  "picTitle":"木坑竹海图片",
  "picSrc":"./images2/19.jpg"
},{
  "id":19,
  "picTitle":"大理古域图片",
  "picSrc":"./images2/20.jpg"
},{
  "id":20,
  "picTitle":"农田图片",
  "picSrc":"./images2/21.jpg"
}],
"title":"广州地铁",
"picAuthor":"广州地铁",
"time":"2019-07-15"
}